gonka_openai/__init__.py
gonka_openai/constants.py
gonka_openai/entities.py
gonka_openai/get_participants_with_proof.py
gonka_openai/gonka_openai.py
gonka_openai/utils.py
gonka_openai/ics23/__init__.py
gonka_openai/ics23/cosmos/__init__.py
gonka_openai/ics23/cosmos/ics23/__init__.py
gonka_openai/ics23/cosmos/ics23/v1/__init__.py
gonka_openai/ics23/cosmos/ics23/v1/proofs_pb2.py
gonka_openai-0.2.4.dist-info/METADATA
gonka_openai-0.2.4.dist-info/WHEEL
gonka_openai-0.2.4.dist-info/top_level.txt
gonka_openai-0.2.4.dist-info/RECORD
