Metadata-Version: 2.4
Name: gonka-openai
Version: 0.2.4
Summary: OpenAI client with Gonka network integration
Home-page: https://github.com/product-science/gonka-openai
Author: David Liberman
Author-email: david@liberman.net
Classifier: Programming Language :: Python :: 3
Classifier: License :: OSI Approved :: MIT License
Classifier: Operating System :: OS Independent
Requires-Python: >=3.7
Requires-Dist: openai>=1.0.0
Requires-Dist: python-dotenv>=0.19.0
Requires-Dist: secp256k1>=0.14.0
Requires-Dist: ecdsa>=0.18.0
Requires-Dist: bech32>=1.2.0
Requires-Dist: requests>=2.25.0
Requires-Dist: protobuf>=4.25.0
Provides-Extra: dev
Requires-Dist: pytest>=6.0.0; extra == "dev"
Requires-Dist: black>=21.5b2; extra == "dev"
Requires-Dist: isort>=5.9.1; extra == "dev"
Requires-Dist: mypy>=0.812; extra == "dev"
Dynamic: author
Dynamic: author-email
Dynamic: classifier
Dynamic: description
Dynamic: description-content-type
Dynamic: home-page
Dynamic: provides-extra
Dynamic: requires-dist
Dynamic: requires-python
Dynamic: summary
